README.md
setup.py
yorpo.py
yorpo.egg-info/PKG-INFO
yorpo.egg-info/SOURCES.txt
yorpo.egg-info/dependency_links.txt
yorpo.egg-info/entry_points.txt
yorpo.egg-info/top_level.txt